bdns_plus/__init__.py
bdns_plus/_version.py
bdns_plus/abbreviations.py
bdns_plus/config.py
bdns_plus/default_fields.py
bdns_plus/docs.py
bdns_plus/env.py
bdns_plus/gen_idata.py
bdns_plus/gen_levels_volumes.py
bdns_plus/ifc.py
bdns_plus/iref.py
bdns_plus/iref_io.py
bdns_plus/models.py
bdns_plus/tag.py
bdns_plus/ui.py
bdns_plus/data/BDNS_Abbreviations_Register.csv
bdns_plus/examples/__init__.py
bdns_plus/examples/electrical_system.py
bdns_plus/examples/no_config.py
bdns_plus/examples/project_defs.py
bdns_plus-0.3.1.dist-info/METADATA
bdns_plus-0.3.1.dist-info/WHEEL
bdns_plus-0.3.1.dist-info/RECORD
