Metadata-Version: 2.4
Name: bdns-plus
Version: 0.3.1
Summary: bdns references + configurable equipment references for drawings
Author-email: jgunstone <j.gunstone@maxfordham.com>
Requires-Python: >=3.11
Requires-Dist: bsdd<0.9,>=0.8.2
Requires-Dist: ipyautoui<0.10,>=0.9.0
Requires-Dist: pycountry<25,>=24.6.1
Requires-Dist: pydantic-settings<3,>=2.8.0
Requires-Dist: pydantic<3,>=2.8.0
Requires-Dist: pyrulefilter<0.6,>=0.5.0
